LICENSE
README.md
setup.py
conbo/__init__.py
conbo/confidence_bounds.py
conbo.egg-info/PKG-INFO
conbo.egg-info/SOURCES.txt
conbo.egg-info/dependency_links.txt
conbo.egg-info/requires.txt
conbo.egg-info/top_level.txt