Metadata-Version: 2.1
Name: conbo
Version: 0.1.1
Summary: A package for bounding properties of random variables with high confidence.
Home-page: https://github.com/yascho/conbo
Author: Yan Scholten
Author-email: yan.scholten@tum.de
License: MIT
Classifier: Intended Audience :: Science/Research
Classifier: Programming Language :: Python :: 3.8
Classifier: Programming Language :: Python :: 3.11
License-File: LICENSE
Requires-Dist: statsmodels==0.14.4
Requires-Dist: numpy>=1.24.4
